k2hr3client/__init__.py
k2hr3client/acr.py
k2hr3client/api.py
k2hr3client/exception.py
k2hr3client/extdata.py
k2hr3client/http.py
k2hr3client/list.py
k2hr3client/policy.py
k2hr3client/resource.py
k2hr3client/role.py
k2hr3client/service.py
k2hr3client/tenant.py
k2hr3client/token.py
k2hr3client/userdata.py
k2hr3client/version.py
k2hr3client-1.1.3.dist-info/licenses/AUTHORS.rst
k2hr3client-1.1.3.dist-info/licenses/LICENSE
k2hr3client-1.1.3.dist-info/METADATA
k2hr3client-1.1.3.dist-info/WHEEL
k2hr3client-1.1.3.dist-info/top_level.txt
k2hr3client-1.1.3.dist-info/RECORD
