Metadata-Version: 2.4
Name: k2hr3client
Version: 1.1.3
Summary: k2hr3client for python
Author-email: Hirotaka Wakabayashi <hiwakaba@lycorp.co.jp>, Takeshi Nakatani <ggtakec@gmail.com>
Maintainer-email: Hirotaka Wakabayashi <hiwakaba@lycorp.co.jp>, Takeshi Nakatani <ggtakec@gmail.com>
License: MIT License
Project-URL: Homepage, https://github.com/yahoojapan/k2hr3client_python
Project-URL: Documentation, https://k2hr3client-python.readthedocs.org
Project-URL: Repository, https://github.com/yahoojapan/k2hr3client_python.git
Project-URL: Bug Tracker, https://github.com/yahoojapan/k2hr3client_python/issues
Project-URL: Changelog, https://github.com/yahoojapan/k2hr3client_python/blob/master/HISTORY.rst
Keywords: k2hr3,antpickax,OpenStack,iaas,k2hdkc_dbaas
Classifier: Development Status :: 4 - Beta
Classifier: Programming Language :: Python
Classifier: Environment :: Console
Classifier: Environment :: OpenStack
Classifier: Intended Audience :: Developers
Classifier: Intended Audience :: Information Technology
Classifier: License :: OSI Approved :: MIT License
Classifier: Programming Language :: Python :: 3
Classifier: Programming Language :: Python :: 3.9
Requires-Python: >=3.9
License-File: LICENSE
License-File: AUTHORS.rst
Dynamic: license-file
